assets/logo.png
assets/css/index.css
assets/html/index.html
assets/js/index.js
pycells_api/__init__.py
pycells_api/cli.py
pycells_api/main.py
pycells_api/schemas.py
pycells_mds/__init__.py
pycells_mds/core.py
pycells_mds/managers.py
pycells_mds/models.py
pycells_mds/session.py
pycells_mds/users.py
pycells_mds/wrappers.py
pycells_mds/cli/cli_pyxel.py
pycells_mds-0.3.0.dist-info/licenses/LICENSE
pycells_mds-0.3.0.dist-info/METADATA
pycells_mds-0.3.0.dist-info/WHEEL
pycells_mds-0.3.0.dist-info/entry_points.txt
pycells_mds-0.3.0.dist-info/top_level.txt
pycells_mds-0.3.0.dist-info/RECORD
