Metadata-Version: 2.4
Name: pycells_mds
Version: 0.3.0
Summary: Multidimensional Data Structures for Python.
Author-email: Zhandos Mambetali <zhandos.mambetali@gmail.com>
License-Expression: MIT
Project-URL: Homepage, https://pycells.com
Project-URL: Repository, https://github.com/Jandos77/pycells_mds
Project-URL: Issues, https://github.com/Jandos77/pycells_mds/issues
Project-URL: Contact, https://wa.me/77014577360
Keywords: database,multidimensional,data structures,sqlalchemy,pycells
Classifier: Development Status :: 3 - Alpha
Classifier: Intended Audience :: Developers
Classifier: Programming Language :: Python :: 3
Classifier: Programming Language :: Python :: 3.9
Classifier: Programming Language :: Python :: 3.10
Classifier: Programming Language :: Python :: 3.11
Classifier: Topic :: Software Development :: Libraries
Requires-Python: >=3.9
License-File: LICENSE
Requires-Dist: sqlalchemy
Requires-Dist: numpy
Requires-Dist: redis
Requires-Dist: fastapi
Requires-Dist: uvicorn[standard]
Dynamic: license-file
